test_maker/__init__.py
test_maker/test_maker.py
test_maker-0.0.1.dist-info/METADATA
test_maker-0.0.1.dist-info/WHEEL
test_maker-0.0.1.dist-info/licenses/LICENSE
test_maker-0.0.1.dist-info/RECORD
