Metadata-Version: 2.1
Name: test_maker
Version: 0.0.1
Summary: A simple package for making test questions based on reading material.
Project-URL: Homepage, https://github.com/yishairasowsky
Project-URL: Bug Tracker, https://github.com/yishairasowsky
Author-email: Yishai Rasowsky <yishairasowsky@gmail.com>
License: MIT License
Classifier: License :: OSI Approved :: MIT License
Classifier: Operating System :: OS Independent
Classifier: Programming Language :: Python :: 3
Requires-Python: >=3.7
